{
  "title": "Just Cool Devs",
  "palette": "blue",
  "header": {
    "type": "header",
    "title": "Just Cool Devs",
    "logo_img": "/images/justcooldevs-logo-final.png",
    "has_nav": true,
    "nav_links": [
      {
        "type": "action",
        "label": "Home",
        "url": "/"
      },
      {
        "type": "action",
        "label": "Features",
        "url": "/features"
      },
      {
        "type": "action",
        "label": "Pricing",
        "url": "/pricing"
      }
    ]
  },
  "footer": {
    "subscribe_title": "Subscribe",
    "subscribe_content": "Stay up to date with our latest developments.",
    "has_subscribe": true,
    "social_title": "Community",
    "social_links": [
      {
        "type": "action",
        "label": "Linkedin",
        "url": "https://www.linkedin.com/in/rjay-ortiz",
        "new_window": true
      },
      {
        "type": "action",
        "label": "GitHub",
        "url": "https://github.com/J4CODE",
        "new_window": true
      },
      {
        "type": "action",
        "label": "Twitter",
        "url": "https://twitter.com/oz4code?lang=en",
        "new_window": true
      }
    ],
    "tagline": "Coding the future.",
    "logo_img": "/images/justcooldevs-logo-white.png",
    "has_social": true,
    "content": "2021 &copy;",
    "links": [
      {
        "type": "action",
        "label": "Built with the JAMStack",
        "url": "https://jamstack.org",
        "new_window": true
      }
    ],
    "type": "footer",
    "nav_title": "Company",
    "nav_links": [
      {
        "type": "action",
        "label": "Contact",
        "url": "/contact"
      }
    ],
    "has_nav": true
  }
}